{"__type__":"sp.SkeletonData","_name":"lingquyem","_rawFiles":["raw-skeleton.json"],"_skeletonJson":{"skeleton":{"hash":"H93UAaHqq7K8wpPBwWeTFLULQXQ","spine":"2.1.27","width":772,"height":722,"images":"./images/"},"bones":[{"name":"root"},{"name":"bone","parent":"root","scaleX":2,"scaleY":2}],"slots":[{"name":"4","bone":"bone","attachment":"4"},{"name":"5","bone":"root","attachment":"5"},{"name":"6","bone":"root","attachment":"6"},{"name":"9","bone":"root","attachment":"9"},{"name":"13","bone":"root"}],"skins":{"default":{"4":{"4":{"width":386,"height":361}},"5":{"5":{"width":347,"height":355}},"6":{"6":{"width":199,"height":206}},"9":{"9":{"y":210.41,"width":546,"height":129}}}},"animations":{"animation":{"slots":{"4":{"color":[{"time":0,"color":"ffffff80"}]},"5":{"color":[{"time":0,"color":"ffffff6b"},{"time":2,"color":"ffffffff"},{"time":4,"color":"ffffff6b"}]}},"bones":{"bone":{"rotate":[{"time":0,"angle":0},{"time":2,"angle":181},{"time":4,"angle":1}]}}}}},"_atlasText":"\r\nlingquyem.png\r\nformat: RGBA8888\r\nfilter: Linear,Linear\r\nrepeat: none\r\n4\r\n  rotate: false\r\n  xy: 2, 204\r\n  size: 386, 361\r\n  orig: 386, 361\r\n  offset: 0, 0\r\n  index: -1\r\n5\r\n  rotate: false\r\n  xy: 390, 210\r\n  size: 347, 355\r\n  orig: 347, 355\r\n  offset: 0, 0\r\n  index: -1\r\n6\r\n  rotate: false\r\n  xy: 550, 2\r\n  size: 199, 206\r\n  orig: 199, 206\r\n  offset: 0, 0\r\n  index: -1\r\n9\r\n  rotate: false\r\n  xy: 2, 73\r\n  size: 546, 129\r\n  orig: 546, 129\r\n  offset: 0, 0\r\n  index: -1\r\n","atlasUrl":{"__uuid__":"eacZOMksVCM6lMK7osr0hR"},"textures":[{"__uuid__":"86D+hbBG9M6KcI80TJ+Z4u"}]}