[{"__type__":"cc.SpriteFrame","content":{"name":"common-040","texture":"adt/klFQBIrZHh7B3YoktH","rect":[198,277,118,118],"offset":[0,0],"originalSize":[118,118]}},{"__type__":"cc.SpriteFrame","content":{"name":"common-042","texture":"adt/klFQBIrZHh7B3YoktH","rect":[558,241,118,118],"offset":[0,0],"originalSize":[118,118]}},{"__type__":"cc.SpriteFrame","content":{"name":"common-010","texture":"adt/klFQBIrZHh7B3YoktH","rect":[578,938,36,37],"offset":[0,0],"originalSize":[36,37]}},{"__type__":"cc.SpriteFrame","content":{"name":"common-032","texture":"adt/klFQBIrZHh7B3YoktH","rect":[558,1,118,118],"offset":[0,0],"originalSize":[118,118]}},{"__type__":"cc.SpriteFrame","content":{"name":"common-008","texture":"adt/klFQBIrZHh7B3YoktH","rect":[693,938,249,85],"offset":[0,0],"originalSize":[249,85]}},{"__type__":"cc.SpriteFrame","content":{"name":"common-071","texture":"adt/klFQBIrZHh7B3YoktH","rect":[756,252,222,65],"offset":[0,0],"originalSize":[222,65],"rotated":1}},{"__type__":"cc.SpriteFrame","content":{"name":"common-037","texture":"adt/klFQBIrZHh7B3YoktH","rect":[558,121,118,118],"offset":[0,0],"originalSize":[118,118]}},{"__type__":"cc.SpriteFrame","content":{"name":"common-043","texture":"adt/klFQBIrZHh7B3YoktH","rect":[318,361,118,118],"offset":[0,0],"originalSize":[118,118]}},{"__type__":"cc.SpriteFrame","content":{"name":"common-013","texture":"adt/klFQBIrZHh7B3YoktH","rect":[678,331,51,51],"offset":[0,0],"originalSize":[51,51]}},{"__type__":"cc.SpriteFrame","content":{"name":"common-030","texture":"adt/klFQBIrZHh7B3YoktH","rect":[318,1,118,118],"offset":[0,0],"originalSize":[118,118]}},{"__type__":"cc.SpriteFrame","content":{"name":"common-057","texture":"adt/klFQBIrZHh7B3YoktH","rect":[895,1,194,58],"offset":[0,0],"originalSize":[194,58],"rotated":1}},{"__type__":"cc.SpriteFrame","content":{"name":"common-047","texture":"adt/klFQBIrZHh7B3YoktH","rect":[536,458,97,91],"offset":[0,0],"originalSize":[97,91],"rotated":1}},{"__type__":"cc.SpriteFrame","content":{"name":"common-023","texture":"adt/klFQBIrZHh7B3YoktH","rect":[1,1002,604,12],"offset":[0,0],"originalSize":[604,12],"capInsets":[90,0,97,0]}},{"__type__":"cc.SpriteFrame","content":{"name":"common-034","texture":"adt/klFQBIrZHh7B3YoktH","rect":[198,157,118,118],"offset":[0,0],"originalSize":[118,118]}},{"__type__":"cc.SpriteFrame","content":{"name":"common-000","texture":"adt/klFQBIrZHh7B3YoktH","rect":[474,938,102,39],"offset":[0,0],"originalSize":[102,39]}},{"__type__":"cc.SpriteFrame","content":{"name":"common-049","texture":"adt/klFQBIrZHh7B3YoktH","rect":[895,370,75,75],"offset":[0,0],"originalSize":[75,75]}},{"__type__":"cc.SpriteFrame","content":{"name":"common-072","texture":"adt/klFQBIrZHh7B3YoktH","rect":[78,121,82,21],"offset":[0,0],"originalSize":[82,21]}},{"__type__":"cc.SpriteFrame","content":{"name":"common-031","texture":"adt/klFQBIrZHh7B3YoktH","rect":[438,1,118,118],"offset":[0,0],"originalSize":[118,118]}},{"__type__":"cc.SpriteFrame","content":{"name":"common-016","texture":"adt/klFQBIrZHh7B3YoktH","rect":[382,481,50,50],"offset":[0,0],"originalSize":[50,50]}},{"__type__":"cc.SpriteFrame","content":{"name":"common-002","texture":"adt/klFQBIrZHh7B3YoktH","rect":[651,986,18,31],"offset":[0,0],"originalSize":[18,31],"rotated":1}},{"__type__":"cc.SpriteFrame","content":{"name":"common-044","texture":"adt/klFQBIrZHh7B3YoktH","rect":[891,601,64,64],"offset":[0,0],"originalSize":[64,64]}},{"__type__":"cc.SpriteFrame","content":{"name":"common-007","texture":"adt/klFQBIrZHh7B3YoktH","rect":[756,1,249,87],"offset":[0,0],"originalSize":[249,87],"rotated":1}},{"__type__":"cc.SpriteAtlas","_name":"common.plist","_spriteFrames":{"common-000":{"__uuid__":"46lTquHolELpoxZGx7mvrw"},"common-001":{"__uuid__":"7bViijAAxPAJ3GC0kbLBeJ"},"common-002":{"__uuid__":"4eQfrZVQZEx68mOUI/bYxx"},"common-003":{"__uuid__":"e94Ytu+ABJzpozmBvVw+L6"},"common-004":{"__uuid__":"e1QOiflj1I3pRxANYjB1pe"},"common-005":{"__uuid__":"a9FSNayVlJIoWCtB5uQNHs"},"common-006":{"__uuid__":"b0xmoHuiZNIJ/OSJpVZnTf"},"common-007":{"__uuid__":"56zzU3NXpMVpoLpltjSE4O"},"common-008":{"__uuid__":"15sinZ6OZIR6g9phvu4VTO"},"common-009":{"__uuid__":"f5FjRtjexCPY+pyd/p7hWK"},"common-010":{"__uuid__":"15Jj34dzdCU6W7xi4y2MC3"},"common-011":{"__uuid__":"9ffWDqIPpNboLW9kkOnfPc"},"common-012":{"__uuid__":"d9U3iHRzNInoizd69fRPkK"},"common-013":{"__uuid__":"1eht6J69ZI/bbsgE4KM9LU"},"common-014":{"__uuid__":"f7AUp/Zu1MUJC23X5vXQOA"},"common-015":{"__uuid__":"83ElG1t7tGhoa+ejFoBHYt"},"common-016":{"__uuid__":"4dnb5uuMVIvrzaQVNPAiFJ"},"common-017":{"__uuid__":"a5pG/Jt/5J+r6fHK0PEWxr"},"common-018":{"__uuid__":"e7vVqgJmRDE4V+2rnafS6u"},"common-019":{"__uuid__":"e3bFleV9xK6qHY7lMmC3ZB"},"common-020":{"__uuid__":"84nfGlH3lIZZ02kAiwTkzQ"},"common-021":{"__uuid__":"deURB2KWhBPpifL1bzcDBv"},"common-022":{"__uuid__":"aeeuZBGglAB7xcMBR3Pt3W"},"common-023":{"__uuid__":"40LxeUd1tLlpJweUxO2gWx"},"common-024":{"__uuid__":"75SjIwHPVARp5AtVaeM5Wl"},"common-025":{"__uuid__":"b68VhAF+tLcKoW8BmknNB4"},"common-026":{"__uuid__":"cb1sHL3khITrjFSOV6eN6W"},"common-027":{"__uuid__":"d0wP93xtJPXoh76L73l44N"},"common-028":{"__uuid__":"d04qaGxuVEzYnZpbxWsXeU"},"common-029":{"__uuid__":"f1IcJ3JydKPpGa4OcS3ri1"},"common-030":{"__uuid__":"2dRsibWg5BsqOMHsAgMzvD"},"common-031":{"__uuid__":"4ckMyjSfxB1JPnObve1KHK"},"common-032":{"__uuid__":"15StgoGClNX7lkw1R2melX"},"common-033":{"__uuid__":"61tzT1sH5IrZY/hkzhCqUU"},"common-034":{"__uuid__":"43PetyUIhE+44dM1szZO7l"},"common-035":{"__uuid__":"7ddNJiDQtCJ6CcILThZl8a"},"common-036":{"__uuid__":"6aT9i6GYNGrqLfbkweAb7a"},"common-037":{"__uuid__":"1ak5vOfO9NeIEXqinL9wwE"},"common-038":{"__uuid__":"85h5OwWqJOV5oSPxUVY806"},"common-039":{"__uuid__":"f78YP88wBLnal6Mi1X7puS"},"common-040":{"__uuid__":"003mr5Me9FmplCsssX7zGW"},"common-041":{"__uuid__":"7eAqKIw6ZHM6vgt439AKys"},"common-042":{"__uuid__":"01IsJOXLBE9by5rLsFa3Q8"},"common-043":{"__uuid__":"1bCs803AtPHZa3jB8zo6/n"},"common-044":{"__uuid__":"54Ac6VIu1MaamhAhiW12gF"},"common-045":{"__uuid__":"f2nb5/FBhElK89OxWHxYEp"},"common-046":{"__uuid__":"701yGq751Bi6BTQw2QJom6"},"common-047":{"__uuid__":"3aS+fg8PpLPbSuLMyb7lms"},"common-048":{"__uuid__":"74erO1hlJKK4i1XmOQ64Fg"},"common-049":{"__uuid__":"4723ASCMNII5XGAUmMcC14"},"common-050":{"__uuid__":"83xm5W4aVAMab72zYrQr3Y"},"common-051":{"__uuid__":"e8qw3pUDZDpK32L6ytfgJW"},"common-052":{"__uuid__":"edI9P13DFM+r7f6cYoezZy"},"common-053":{"__uuid__":"971ME+3MVHkKQfVzEXNybW"},"common-054":{"__uuid__":"96f5AG6X5FzIfsV1hc2+Yx"},"common-055":{"__uuid__":"798b1rJ4pMe50akMZtHPgT"},"common-056":{"__uuid__":"7719sl3qtKybJeXq+oXNbx"},"common-057":{"__uuid__":"37SShuMzlJQYXtIa7TXOl5"},"common-058":{"__uuid__":"c0PM+/pZ5D9aq1Pk7iL/+5"},"common-059":{"__uuid__":"cbYcYgfPFDDbZSp+HTse0J"},"common-060":{"__uuid__":"e7FTmNWqlIlKfabUslG6Sb"},"common-061":{"__uuid__":"b0+VMWCwhOTJjFEjFUkpgY"},"common-062":{"__uuid__":"f5ZD1RrfNMg7CXG6WVdFKN"},"common-063":{"__uuid__":"benJUOrz1MBJDjozULXapd"},"common-064":{"__uuid__":"7a9JonCzxBT4BrXqSeFzb4"},"common-065":{"__uuid__":"b4JD0sz0ZP650ZTfMRxd/L"},"common-066":{"__uuid__":"a2ezEOLGxOGLncVGalwWF8"},"common-067":{"__uuid__":"b7HixKTnlF5aj9cS3e/wBv"},"common-068":{"__uuid__":"cbx/sZuzlNspFBlfpNKInY"},"common-069":{"__uuid__":"89WGMBdUpM6aLqWYf4OEba"},"common-070":{"__uuid__":"b58EPnPnNN86op2LktPm6w"},"common-071":{"__uuid__":"18pocli+BGtbBuED6bIed3"},"common-072":{"__uuid__":"4bFSB9xKFKPrtaDIaRgJDR"},"common-073":{"__uuid__":"93cciEYPVERKBBBt6S3AOB"},"common-074":{"__uuid__":"fd7taTC7pF2rxFTUahem5z"},"common-075":{"__uuid__":"f3Da8HU2tGX7UehOCx9OS3"}}},{"__type__":"cc.SpriteFrame","content":{"name":"common-033","texture":"adt/klFQBIrZHh7B3YoktH","rect":[78,157,118,118],"offset":[0,0],"originalSize":[118,118]}},{"__type__":"cc.SpriteFrame","content":{"name":"common-036","texture":"adt/klFQBIrZHh7B3YoktH","rect":[438,121,118,118],"offset":[0,0],"originalSize":[118,118]}},{"__type__":"cc.SpriteFrame","content":{"name":"common-046","texture":"adt/klFQBIrZHh7B3YoktH","rect":[192,397,100,100],"offset":[0,0],"originalSize":[100,100],"capInsets":[22,19,21,25]}},{"__type__":"cc.SpriteFrame","content":{"name":"common-048","texture":"adt/klFQBIrZHh7B3YoktH","rect":[704,1,90,37],"offset":[0,0],"originalSize":[90,37],"rotated":1}},{"__type__":"cc.SpriteFrame","content":{"name":"common-024","texture":"adt/klFQBIrZHh7B3YoktH","rect":[1,980,648,20],"offset":[0,0],"originalSize":[648,20],"capInsets":[127,0,121,0]}},{"__type__":"cc.SpriteFrame","content":{"name":"common-056","texture":"adt/klFQBIrZHh7B3YoktH","rect":[814,526,75,75],"offset":[0,0],"originalSize":[75,75]}},{"__type__":"cc.SpriteFrame","content":{"name":"common-055","texture":"adt/klFQBIrZHh7B3YoktH","rect":[893,524,75,75],"offset":[0,0],"originalSize":[75,75]}},{"__type__":"cc.SpriteFrame","content":{"name":"common-064","texture":"adt/klFQBIrZHh7B3YoktH","rect":[78,397,112,106],"offset":[0,0],"originalSize":[112,106]}},{"__type__":"cc.SpriteFrame","content":{"name":"common-001","texture":"adt/klFQBIrZHh7B3YoktH","rect":[1,697,753,68],"offset":[0,0],"originalSize":[753,68]}},{"__type__":"cc.SpriteFrame","content":{"name":"common-035","texture":"adt/klFQBIrZHh7B3YoktH","rect":[318,121,118,118],"offset":[0,0],"originalSize":[118,118]}},{"__type__":"cc.SpriteFrame","content":{"name":"common-041","texture":"adt/klFQBIrZHh7B3YoktH","rect":[438,241,118,118],"offset":[0,0],"originalSize":[118,118]}},{"__type__":"cc.SpriteFrame","content":{"name":"common-015","texture":"adt/klFQBIrZHh7B3YoktH","rect":[651,938,46,36],"offset":[0,0],"originalSize":[46,36],"rotated":1}},{"__type__":"cc.SpriteFrame","content":{"name":"common-050","texture":"adt/klFQBIrZHh7B3YoktH","rect":[895,447,75,75],"offset":[0,0],"originalSize":[75,75]}},{"__type__":"cc.SpriteFrame","content":{"name":"common-020","texture":"adt/klFQBIrZHh7B3YoktH","rect":[1,1016,690,2],"offset":[0,0],"originalSize":[690,2]}},{"__type__":"cc.SpriteFrame","content":{"name":"common-038","texture":"adt/klFQBIrZHh7B3YoktH","rect":[318,241,118,118],"offset":[0,0],"originalSize":[118,118]}},{"__type__":"cc.SpriteFrame","content":{"name":"common-069","texture":"adt/klFQBIrZHh7B3YoktH","rect":[633,384,95,95],"offset":[0,0],"originalSize":[95,95]}},{"__type__":"cc.SpriteFrame","content":{"name":"common-073","texture":"adt/klFQBIrZHh7B3YoktH","rect":[538,841,155,24],"offset":[0,0],"originalSize":[155,24]}},{"__type__":"cc.SpriteFrame","content":{"name":"common-054","texture":"adt/klFQBIrZHh7B3YoktH","rect":[845,1,324,48],"offset":[0,0],"originalSize":[324,48],"rotated":1,"capInsets":[82,0,64,0]}},{"__type__":"cc.SpriteFrame","content":{"name":"common-053","texture":"adt/klFQBIrZHh7B3YoktH","rect":[974,327,324,48],"offset":[0,0],"originalSize":[324,48],"rotated":1,"capInsets":[70,0,74,0]}},{"__type__":"cc.SpriteFrame","content":{"name":"common-011","texture":"adt/klFQBIrZHh7B3YoktH","rect":[1,874,281,104],"offset":[0,0],"originalSize":[281,104]}},{"__type__":"cc.SpriteFrame","content":{"name":"common-066","texture":"adt/klFQBIrZHh7B3YoktH","rect":[756,660,112,105],"offset":[0,0],"originalSize":[112,105]}},{"__type__":"cc.SpriteFrame","content":{"name":"common-017","texture":"adt/klFQBIrZHh7B3YoktH","rect":[382,533,50,50],"offset":[0,0],"originalSize":[50,50]}},{"__type__":"cc.SpriteFrame","content":{"name":"common-005","texture":"adt/klFQBIrZHh7B3YoktH","rect":[944,856,75,160],"offset":[0,0],"originalSize":[75,160]}},{"__type__":"cc.SpriteFrame","content":{"name":"common-022","texture":"adt/klFQBIrZHh7B3YoktH","rect":[1,1020,2,147],"offset":[0,0],"originalSize":[2,147],"rotated":1}},{"__type__":"cc.SpriteFrame","content":{"name":"common-006","texture":"adt/klFQBIrZHh7B3YoktH","rect":[538,767,174,72],"offset":[0,0],"originalSize":[174,72]}},{"__type__":"cc.SpriteFrame","content":{"name":"common-061","texture":"adt/klFQBIrZHh7B3YoktH","rect":[678,187,89,36],"offset":[0,0],"originalSize":[89,36],"rotated":1}},{"__type__":"cc.SpriteFrame","content":{"name":"common-065","texture":"adt/klFQBIrZHh7B3YoktH","rect":[629,481,94,83],"offset":[0,0],"originalSize":[94,83]}},{"__type__":"cc.SpriteFrame","content":{"name":"common-070","texture":"adt/klFQBIrZHh7B3YoktH","rect":[438,361,96,96],"offset":[0,0],"originalSize":[96,96]}},{"__type__":"cc.SpriteFrame","content":{"name":"common-025","texture":"adt/klFQBIrZHh7B3YoktH","rect":[756,476,78,56],"offset":[0,0],"originalSize":[78,56],"rotated":1}},{"__type__":"cc.SpriteFrame","content":{"name":"common-067","texture":"adt/klFQBIrZHh7B3YoktH","rect":[721,856,213,74],"offset":[0,0],"originalSize":[213,75]}},{"__type__":"cc.SpriteFrame","content":{"name":"common-063","texture":"adt/klFQBIrZHh7B3YoktH","rect":[438,459,94,86],"offset":[0,0],"originalSize":[94,86]}},{"__type__":"cc.SpriteFrame","content":{"name":"common-058","texture":"adt/klFQBIrZHh7B3YoktH","rect":[756,556,102,39],"offset":[0,0],"originalSize":[102,39],"rotated":1}},{"__type__":"cc.SpriteFrame","content":{"name":"common-059","texture":"adt/klFQBIrZHh7B3YoktH","rect":[823,457,67,68],"offset":[0,0],"originalSize":[67,68],"rotated":1}},{"__type__":"cc.SpriteFrame","content":{"name":"common-068","texture":"adt/klFQBIrZHh7B3YoktH","rect":[536,361,95,95],"offset":[0,0],"originalSize":[95,95]}},{"__type__":"cc.SpriteFrame","content":{"name":"common-026","texture":"adt/klFQBIrZHh7B3YoktH","rect":[823,327,128,70],"offset":[0,0],"originalSize":[128,70],"rotated":1,"capInsets":[10,10,10,10]}},{"__type__":"cc.SpriteFrame","content":{"name":"common-027","texture":"adt/klFQBIrZHh7B3YoktH","rect":[974,653,130,42],"offset":[0,0],"originalSize":[130,42],"rotated":1,"capInsets":[16,14,16,14]}},{"__type__":"cc.SpriteFrame","content":{"name":"common-028","texture":"adt/klFQBIrZHh7B3YoktH","rect":[78,1,118,118],"offset":[0,0],"originalSize":[118,118]}},{"__type__":"cc.SpriteFrame","content":{"name":"common-012","texture":"adt/klFQBIrZHh7B3YoktH","rect":[1,767,282,105],"offset":[0,0],"originalSize":[282,105]}},{"__type__":"cc.SpriteFrame","content":{"name":"common-021","texture":"adt/klFQBIrZHh7B3YoktH","rect":[1,1,75,694],"offset":[0,0],"originalSize":[75,694]}},{"__type__":"cc.SpriteFrame","content":{"name":"common-004","texture":"adt/klFQBIrZHh7B3YoktH","rect":[721,767,251,87],"offset":[0,0],"originalSize":[251,87]}},{"__type__":"cc.SpriteFrame","content":{"name":"common-019","texture":"adt/klFQBIrZHh7B3YoktH","rect":[294,481,86,86],"offset":[0,0],"originalSize":[86,86]}},{"__type__":"cc.SpriteFrame","content":{"name":"common-060","texture":"adt/klFQBIrZHh7B3YoktH","rect":[797,603,92,38],"offset":[0,0],"originalSize":[92,38]}},{"__type__":"cc.SpriteFrame","content":{"name":"common-018","texture":"adt/klFQBIrZHh7B3YoktH","rect":[870,667,98,99],"offset":[0,0],"originalSize":[98,99],"rotated":1}},{"__type__":"cc.SpriteFrame","content":{"name":"common-051","texture":"adt/klFQBIrZHh7B3YoktH","rect":[284,938,188,36],"offset":[0,0],"originalSize":[188,36]}},{"__type__":"cc.SpriteFrame","content":{"name":"common-003","texture":"adt/klFQBIrZHh7B3YoktH","rect":[895,197,171,60],"offset":[0,0],"originalSize":[171,60],"rotated":1}},{"__type__":"cc.SpriteFrame","content":{"name":"common-052","texture":"adt/klFQBIrZHh7B3YoktH","rect":[974,1,324,48],"offset":[0,0],"originalSize":[324,48],"rotated":1,"capInsets":[78,0,50,0]}},{"__type__":"cc.SpriteFrame","content":{"name":"common-029","texture":"adt/klFQBIrZHh7B3YoktH","rect":[198,1,118,118],"offset":[0,0],"originalSize":[118,118]}},{"__type__":"cc.SpriteFrame","content":{"name":"common-045","texture":"adt/klFQBIrZHh7B3YoktH","rect":[284,874,435,62],"offset":[0,0],"originalSize":[435,62]}},{"__type__":"cc.SpriteFrame","content":{"name":"common-075","texture":"adt/klFQBIrZHh7B3YoktH","rect":[678,278,51,54],"offset":[0,0],"originalSize":[51,54],"rotated":1}},{"__type__":"cc.SpriteFrame","content":{"name":"common-009","texture":"adt/klFQBIrZHh7B3YoktH","rect":[285,767,251,87],"offset":[0,0],"originalSize":[251,87]}},{"__type__":"cc.SpriteFrame","content":{"name":"common-062","texture":"adt/klFQBIrZHh7B3YoktH","rect":[704,93,92,35],"offset":[0,0],"originalSize":[92,35],"rotated":1}},{"__type__":"cc.SpriteFrame","content":{"name":"common-014","texture":"adt/klFQBIrZHh7B3YoktH","rect":[974,785,48,48],"offset":[0,0],"originalSize":[48,48]}},{"__type__":"cc.SpriteFrame","content":{"name":"common-039","texture":"adt/klFQBIrZHh7B3YoktH","rect":[78,277,118,118],"offset":[0,0],"originalSize":[118,118]}},{"__type__":"cc.SpriteFrame","content":{"name":"common-074","texture":"adt/klFQBIrZHh7B3YoktH","rect":[678,1,154,24],"offset":[0,0],"originalSize":[154,24],"rotated":1}}]